AnnLearner/__init__.py
annkit/__init__.py
annkit/basekit.py
annkit-0.1.9.dist-info/licenses/LICENSE
annkit-0.1.9.dist-info/METADATA
annkit-0.1.9.dist-info/WHEEL
annkit-0.1.9.dist-info/top_level.txt
annkit-0.1.9.dist-info/RECORD
